<Ui xmlns="http://www.blizzard.com/wow/ui/">
    <Script file="MicroButtonAndBagsBar.lua"/>

    <Frame name="MicroButtonAndBagsBarTemplate" mixin="MicroButtonAndBagsBarMixin" virtual="true">
        <Size x="220" y="88"/>
        <Layers>
            <Layer level="BACKGROUND">
                <Texture parentKey="MicroBagBar" file="interface/addons/reduxui/media/textures/actionbars/MicroButtonAndBagsBar">
                    <Size x="220" y="88" />
                    <Anchors>
                        <Anchor point="BOTTOMRIGHT" relativePoint="BOTTOMRIGHT" x="0" y="0"/>
                    </Anchors>
                    <TexCoords left="0.5712890625" right="1" top="0.31640625" bottom="1"/>
                </Texture>
                <Texture parentKey="MicroBagBarEndCap" file="interface/addons/reduxui/media/textures/actionbars/MicroButtonAndBagsBar">
                    <Size x="102" y="88" />
                    <Anchors>
                        <Anchor point="BOTTOMLEFT" relativePoint="BOTTOMLEFT" x="-24" y="0"/>
                    </Anchors>
                    <TexCoords left="0.419921875" right="0.6181640625" top="0.31640625" bottom="1"/>
                </Texture>
            </Layer>
        </Layers>
        <Scripts>
            <OnLoad method="OnLoad"/>
        </Scripts>
    </Frame>
</Ui>